odoo8_addon_partner_contact_birthdate-8.0.1.0.0.99.dev16-py2.7-nspkg.pth
odoo8_addon_partner_contact_birthdate-8.0.1.0.0.99.dev16.dist-info/METADATA
odoo8_addon_partner_contact_birthdate-8.0.1.0.0.99.dev16.dist-info/RECORD
odoo8_addon_partner_contact_birthdate-8.0.1.0.0.99.dev16.dist-info/WHEEL
odoo8_addon_partner_contact_birthdate-8.0.1.0.0.99.dev16.dist-info/namespace_packages.txt
odoo8_addon_partner_contact_birthdate-8.0.1.0.0.99.dev16.dist-info/top_level.txt
odoo_addons/partner_contact_birthdate/README.rst
odoo_addons/partner_contact_birthdate/__init__.py
odoo_addons/partner_contact_birthdate/__openerp__.py
odoo_addons/partner_contact_birthdate/hooks.py
odoo_addons/partner_contact_birthdate/models.py
odoo_addons/partner_contact_birthdate/i18n/de.po
odoo_addons/partner_contact_birthdate/i18n/es.po
odoo_addons/partner_contact_birthdate/i18n/eu.po
odoo_addons/partner_contact_birthdate/i18n/fi.po
odoo_addons/partner_contact_birthdate/i18n/fr.po
odoo_addons/partner_contact_birthdate/i18n/it.po
odoo_addons/partner_contact_birthdate/i18n/nl.po
odoo_addons/partner_contact_birthdate/i18n/partner_contact_birthdate.pot
odoo_addons/partner_contact_birthdate/i18n/sl.po
odoo_addons/partner_contact_birthdate/static/description/icon.png
odoo_addons/partner_contact_birthdate/tests/__init__.py
odoo_addons/partner_contact_birthdate/tests/test_birthdate.py
odoo_addons/partner_contact_birthdate/tests/test_delete.py
odoo_addons/partner_contact_birthdate/views/res_partner.xml
